aqtlib/__init__.py
aqtlib/algo.py
aqtlib/broker.py
aqtlib/instrument.py
aqtlib/objects.py
aqtlib/porter.py
aqtlib/schema.py
aqtlib/universe.py
aqtlib/utils.py
aqtlib/version.py
aqtlib-0.3.2.dist-info/LICENSE
aqtlib-0.3.2.dist-info/METADATA
aqtlib-0.3.2.dist-info/WHEEL
aqtlib-0.3.2.dist-info/top_level.txt
aqtlib-0.3.2.dist-info/RECORD
