Metadata-Version: 2.1
Name: aqtlib
Version: 0.3.2
Summary: Asynchronous Quantitative Trading Library
Home-page: https://github.com/kelvingao/aqtlib
Author: Kelvin Gao
Author-email: 89156201@qq.com
License: MIT
Keywords: aqtlib algo trading interactive brokers tws asyncio
Platform: any
Classifier: Development Status :: 2 - Pre-Alpha
Classifier: Intended Audience :: Developers
Classifier: Topic :: Office/Business :: Financial :: Investment
Classifier: License :: OSI Approved :: MIT License
Classifier: Programming Language :: Python :: 3.6
Classifier: Programming Language :: Python :: 3.7
Requires-Python: >=3.6
Requires-Dist: ib-insync
Requires-Dist: asyncpg
Requires-Dist: sqlalchemy
